slack_report.py
slack_report-0.1.0.dist-info/LICENSE
slack_report-0.1.0.dist-info/METADATA
slack_report-0.1.0.dist-info/WHEEL
slack_report-0.1.0.dist-info/entry_points.txt
slack_report-0.1.0.dist-info/top_level.txt
slack_report-0.1.0.dist-info/RECORD
